mcp_video_service/__init__.py
mcp_video_service/__main__.py
mcp_video_service/services/video_service.py
mcp_video_extraction-0.1.6.dist-info/METADATA
mcp_video_extraction-0.1.6.dist-info/WHEEL
mcp_video_extraction-0.1.6.dist-info/entry_points.txt
mcp_video_extraction-0.1.6.dist-info/RECORD
