Metadata-Version: 2.4
Name: mcp-video-extraction
Version: 0.1.6
Summary: A Model Context Protocol server that provides text extraction capabilities from various video platforms and audio files, supporting multiple platforms like YouTube, Bilibili, TikTok, and more using Whisper for high-quality speech recognition
Project-URL: Homepage, https://github.com/yourusername/mcp-video-extraction
Project-URL: Repository, https://github.com/yourusername/mcp-video-extraction.git
Author: Seazhang
Maintainer-email: Seazhang <sealing.pp2@gmail.com>
License: MIT
Keywords: audio,mcp,transcription,video,whisper,youtube-dl
Classifier: Development Status :: 3 - Alpha
Classifier: Intended Audience :: Developers
Classifier: License :: OSI Approved :: MIT License
Classifier: Programming Language :: Python :: 3
Classifier: Programming Language :: Python :: 3.10
Classifier: Programming Language :: Python :: 3.11
Requires-Python: >=3.10
Requires-Dist: mcp[cli]>=1.1.3
Requires-Dist: openai-whisper>=20231117
Requires-Dist: pydantic>=2.0.0
Requires-Dist: pyyaml>=6.0.2
Requires-Dist: yt-dlp>=2024.3.10
